odoo/addons/account_payment_order_return/README.rst
odoo/addons/account_payment_order_return/__init__.py
odoo/addons/account_payment_order_return/__manifest__.py
odoo/addons/account_payment_order_return/i18n/account_payment_order_return.pot
odoo/addons/account_payment_order_return/i18n/ca.po
odoo/addons/account_payment_order_return/i18n/ca_ES.po
odoo/addons/account_payment_order_return/i18n/de.po
odoo/addons/account_payment_order_return/i18n/es.po
odoo/addons/account_payment_order_return/i18n/fr.po
odoo/addons/account_payment_order_return/readme/CONTRIBUTORS.rst
odoo/addons/account_payment_order_return/readme/DESCRIPTION.rst
odoo/addons/account_payment_order_return/readme/INSTALL.rst
odoo/addons/account_payment_order_return/readme/USAGE.rst
odoo/addons/account_payment_order_return/static/description/icon.png
odoo/addons/account_payment_order_return/static/description/index.html
odoo/addons/account_payment_order_return/tests/__init__.py
odoo/addons/account_payment_order_return/tests/test_account_payment_order_return.py
odoo/addons/account_payment_order_return/wizards/__init__.py
odoo/addons/account_payment_order_return/wizards/account_payment_line_create.py
odoo/addons/account_payment_order_return/wizards/account_payment_line_create_view.xml
odoo13_addon_account_payment_order_return-13.0.1.0.3.dist-info/METADATA
odoo13_addon_account_payment_order_return-13.0.1.0.3.dist-info/WHEEL
odoo13_addon_account_payment_order_return-13.0.1.0.3.dist-info/top_level.txt
odoo13_addon_account_payment_order_return-13.0.1.0.3.dist-info/RECORD
